README.rst
setup.py
nestegg/__init__.py
nestegg/main.py
nestegg.egg-info/PKG-INFO
nestegg.egg-info/SOURCES.txt
nestegg.egg-info/dependency_links.txt
nestegg.egg-info/entry_points.txt
nestegg.egg-info/requires.txt
nestegg.egg-info/top_level.txt
nestegg/views/all_packages.tpl
nestegg/views/package.tpl