Metadata-Version: 1.0
Name: nestegg
Version: 0.0.1alpha2
Summary: Lightweight pypi mirror and continuous integration server
Home-page: http://github.com/dnene/nestegg
Author: Dhananjay Nene
Author-email: dhananjay.nene@gmail.com
License: The MIT License (MIT)
Keywords: pypi mirror build release packages
Platform: UNKNOWN
